diojit/__init__.py
diojit/absint/__init__.py
diojit/absint/abs.py
diojit/absint/intrinsics.py
diojit/absint/prescr.py
diojit/codegen/__init__.py
diojit/codegen/julia.py
diojit/runtime/__init__.py
diojit/runtime/julia_rt.py
diojit/stack2reg/__init__.py
diojit/stack2reg/cflags.py
diojit/stack2reg/opcodes.py
diojit/stack2reg/translate.py
diojit/user/__init__.py
diojit/user/client.py
diojit-0.1.5.dist-info/LICENSE
diojit-0.1.5.dist-info/METADATA
diojit-0.1.5.dist-info/WHEEL
diojit-0.1.5.dist-info/entry_points.txt
diojit-0.1.5.dist-info/top_level.txt
diojit-0.1.5.dist-info/RECORD
