Metadata-Version: 2.1
Name: diojit
Version: 0.1.5
Summary: A general-purpose JIT for CPython.
Home-page: https://github.com/thautwarm/diojit
Author: thautwarm
Author-email: twshere@outlook.com
License: mit
Keywords: Just-In-Time,JIT,compiler
Platform: any
Classifier: Programming Language :: Python :: 3.6
Classifier: Programming Language :: Python :: 3.7
Classifier: Programming Language :: Python :: Implementation :: CPython
Requires-Python: >=3.8.0
Requires-Dist: pyrsistent
Requires-Dist: julia
